vaillant_netatmo_api/__init__.py
vaillant_netatmo_api/auth.py
vaillant_netatmo_api/auth_test.py
vaillant_netatmo_api/base.py
vaillant_netatmo_api/errors.py
vaillant_netatmo_api/errors_test.py
vaillant_netatmo_api/home.py
vaillant_netatmo_api/thermostat.py
vaillant_netatmo_api/thermostat_auth.py
vaillant_netatmo_api/thermostat_home_test.py
vaillant_netatmo_api/thermostat_program_test.py
vaillant_netatmo_api/thermostat_test.py
vaillant_netatmo_api/time.py
vaillant_netatmo_api/token.py
vaillant_netatmo_api/token_test.py
vaillant_netatmo_api-0.13.1.dist-info/licenses/LICENSE
vaillant_netatmo_api-0.13.1.dist-info/METADATA
vaillant_netatmo_api-0.13.1.dist-info/WHEEL
vaillant_netatmo_api-0.13.1.dist-info/top_level.txt
vaillant_netatmo_api-0.13.1.dist-info/RECORD
